MANIFEST.in
README.rst
setup.py
docs/HISTORY.txt
docs/LICENSE.GPL
docs/LICENSE.txt
ftw/__init__.py
ftw.linkchecker.egg-info/PKG-INFO
ftw.linkchecker.egg-info/SOURCES.txt
ftw.linkchecker.egg-info/dependency_links.txt
ftw.linkchecker.egg-info/entry_points.txt
ftw.linkchecker.egg-info/namespace_packages.txt
ftw.linkchecker.egg-info/not-zip-safe
ftw.linkchecker.egg-info/requires.txt
ftw.linkchecker.egg-info/top_level.txt
ftw/linkchecker/__init__.py
ftw/linkchecker/cell_format.py
ftw/linkchecker/configure.zcml
ftw/linkchecker/interfaces.py
ftw/linkchecker/linkchecker.py
ftw/linkchecker/pool_with_logging.py
ftw/linkchecker/report_generating.py
ftw/linkchecker/report_mailer.py
ftw/linkchecker/test_setup.py
ftw/linkchecker/testing.py
ftw/linkchecker/Extensions/__init__.py
ftw/linkchecker/Extensions/install.py
ftw/linkchecker/command/__init__.py
ftw/linkchecker/command/broken_link.py
ftw/linkchecker/command/checking_links.py
ftw/linkchecker/tests/__init__.py
ftw/linkchecker/tests/builders.py
ftw/linkchecker/tests/helper_generating_excel.py
ftw/linkchecker/tests/test_functionality.py
ftw/linkchecker/tests/test_report_upload.py
ftw/linkchecker/tests/exemplar_data/__init__.py
ftw/linkchecker/tests/exemplar_data/exemplar_config.py
ftw/linkchecker/tests/exemplar_data/expected_excel_sheet_outcome.xlsx